ichatbio/__init__.py
ichatbio/agent.py
ichatbio/agent_executor.py
ichatbio/agent_response.py
ichatbio/server.py
ichatbio/types.py
ichatbio_sdk-0.2.2.dist-info/METADATA
ichatbio_sdk-0.2.2.dist-info/WHEEL
ichatbio_sdk-0.2.2.dist-info/licenses/LICENSE
ichatbio_sdk-0.2.2.dist-info/RECORD
