Metadata-Version: 2.3
Name: ichatbio-sdk
Version: 0.2.2
Summary: A framework which allows AI agents to interact with iChatBio using the A2A protocol.
Project-URL: repository, https://github.com/acislab/ichatbio-sdk
Author-email: Michael Elliott <mielliott@ufl.edu>, Manny Luciano <mlluciano@ufl.edu>
License: MIT License
Keywords: AI,biodiversity,iChatBio,research,science
Classifier: Operating System :: OS Independent
Classifier: Programming Language :: Python :: 3
Requires-Python: >=3.10
Requires-Dist: a2a-sdk==0.2.10
Requires-Dist: anyio~=4.9.0
Requires-Dist: attrs~=25.3.0
Requires-Dist: pydantic~=2.11.4
Requires-Dist: typing-extensions~=4.13.2
Requires-Dist: uvicorn~=0.34.2
Provides-Extra: example
Requires-Dist: dotenv~=0.9.9; extra == 'example'
Requires-Dist: instructor~=1.8.2; extra == 'example'
Requires-Dist: openai~=1.79.0; extra == 'example'
Requires-Dist: pytest-asyncio~=1.0.0a1; extra == 'example'
Requires-Dist: pytest~=8.3.5; extra == 'example'
Requires-Dist: python-dotenv~=1.1.0; extra == 'example'
